[
  {
    "id": 1,
    "name": "Nicc",
    "lastName": "Smith",
    "email": "nicc@example.com",
    "age": 35,
    "gender": "male",
    "city": "Vancouver",
    "country": "Canada",
    "occupation": "Software Engineer",
    "hobbies": ["Gaming", "Reading", "Hiking"],
    "favoriteColor": "Blue",
    "languages": ["English", "Spanish"],
    "postalCode": "V6B 6B1",
    "streetAddress": "123 Maple Street",
    "province": "BC",
    "phone_number": "+16041234567",
    "birthday": "1988-03-15",
    "profile_picture": "nicc.png",
    "created_at": "2023-01-05",
    "last_active": "2023-02-09"
  },
  {
    "id": 2,
    "name": "Coye",
    "lastName": "Johnson",
    "email": "coye@example.com",
    "age": 28,
    "gender": "male",
    "city": "Chicago",
    "country": "USA",
    "occupation": "Graphic Designer",
    "hobbies": ["Photography", "Cooking", "Traveling"],
    "favoriteColor": "Green",
    "languages": ["English", "French"],
    "postalCode": "60601",
    "streetAddress": "456 Oak Street",
    "state": "IL",
    "phone_number": "+13121234567",
    "birthday": "1995-07-22",
    "profile_picture": "coye.png",
    "created_at": "2023-02-10",
    "last_active": "2023-02-24"
  },
  {
    "id": 3,
    "name": "Chris",
    "lastName": "Brown",
    "email": "chris@example.com",
    "age": 40,
    "gender": "male",
    "city": "Austin",
    "country": "USA",
    "occupation": "Musician",
    "hobbies": ["Playing Guitar", "Songwriting", "Hiking"],
    "favoriteColor": "Red",
    "languages": ["English", "German"],
    "postalCode": "78701",
    "streetAddress": "789 Cedar Avenue",
    "state": "TX",
    "phone_number": "+15121234567",
    "birthday": "1983-11-30",
    "profile_picture": "chris.png",
    "created_at": "2023-03-01",
    "last_active": "2023-03-15"
  },
  {
    "id": 4,
    "name": "Tyler",
    "lastName": "Davis",
    "email": "tyler@example.com",
    "age": 33,
    "gender": "male",
    "city": "Seattle",
    "country": "USA",
    "occupation": "Software Developer",
    "hobbies": ["Programming", "Gaming", "Reading"],
    "favoriteColor": "Orange",
    "languages": ["English", "Japanese"],
    "postalCode": "98101",
    "streetAddress": "101 Pine Street",
    "state": "WA",
    "phone_number": "+12061234567",
    "birthday": "1990-05-17",
    "profile_picture": "tyler.png",
    "created_at": "2023-04-02",
    "last_active": "2023-04-18"
  },
  {
    "id": 5,
    "name": "Curtis",
    "lastName": "Evans",
    "email": "curtis@example.com",
    "age": 45,
    "gender": "male",
    "city": "Miami",
    "country": "USA",
    "occupation": "Business Analyst",
    "hobbies": ["Swimming", "Cooking", "Watching Movies"],
    "favoriteColor": "Purple",
    "languages": ["English", "Spanish"],
    "postalCode": "33101",
    "streetAddress": "234 Palm Avenue",
    "state": "FL",
    "phone_number": "+13051234567",
    "birthday": "1978-09-04",
    "profile_picture": "curtis.png",
    "created_at": "2023-05-03",
    "last_active": "2023-05-19"
  },
  {
    "id": 6,
    "name": "Emma",
    "lastName": "Johnson",
    "email": "emma@example.com",
    "age": 25,
    "gender": "female",
    "city": "Los Angeles",
    "country": "USA",
    "occupation": "Marketing Manager",
    "hobbies": ["Traveling", "Yoga", "Painting"],
    "favoriteColor": "Pink",
    "languages": ["English", "Spanish"],
    "postalCode": "90001",
    "streetAddress": "789 Elm Street",
    "state": "CA",
    "phone_number": "+13231234567",
    "birthday": "1999-02-10",
    "profile_picture": "emma.png",
    "created_at": "2023-06-05",
    "last_active": "2023-06-20"
  },
  {
    "id": 7,
    "name": "Liam",
    "lastName": "Smith",
    "email": "liam@example.com",
    "age": 30,
    "gender": "male",
    "city": "New York City",
    "country": "USA",
    "occupation": "Financial Analyst",
    "hobbies": ["Running", "Playing Piano", "Cooking"],
    "favoriteColor": "Black",
    "languages": ["English", "Mandarin"],
    "postalCode": "10001",
    "streetAddress": "567 Broadway",
    "state": "NY",
    "phone_number": "+12121234567",
    "birthday": "1994-08-28",
    "profile_picture": "liam.png",
    "created_at": "2023-07-10",
    "last_active": "2023-07-25"
  },
  {
    "id": 8,
    "name": "Sophia",
    "lastName": "Miller",
    "email": "sophia@example.com",
    "age": 32,
    "gender": "female",
    "city": "San Francisco",
    "country": "USA",
    "occupation": "Product Manager",
    "hobbies": ["Hiking", "Photography", "Reading"],
    "favoriteColor": "Yellow",
    "languages": ["English", "French"],
    "postalCode": "94101",
    "streetAddress": "101 Market Street",
    "state": "CA",
    "phone_number": "+14151234567",
    "birthday": "1990-12-15",
    "profile_picture": "sophia.png",
    "created_at": "2023-08-15",
    "last_active": "2023-08-30"
  },
  {
    "id": 9,
    "name": "Noah",
    "lastName": "Garcia",
    "email": "noah@example.com",
    "age": 27,
    "gender": "male",
    "city": "Houston",
    "country": "USA",
    "occupation": "Data Scientist",
    "hobbies": ["Chess", "Soccer", "Cooking"],
    "favoriteColor": "Grey",
    "languages": ["English", "Spanish"],
    "postalCode": "77001",
    "streetAddress": "234 Main Street",
    "state": "TX",
    "phone_number": "+17131234567",
    "birthday": "1997-04-05",
    "profile_picture": "noah.png",
    "created_at": "2023-09-10",
    "last_active": "2023-09-25"
  },
  {
    "id": 10,
    "name": "Ava",
    "lastName": "Martinez",
    "email": "ava@example.com",
    "age": 29,
    "gender": "female",
    "city": "Denver",
    "country": "USA",
    "occupation": "Architect",
    "hobbies": ["Painting", "Skiing", "Traveling"],
    "favoriteColor": "Turquoise",
    "languages": ["English", "Italian"],
    "postalCode": "80201",
    "streetAddress": "345 Oak Avenue",
    "state": "CO",
    "phone_number": "+13031234567",
    "birthday": "1993-10-20",
    "profile_picture": "ava.png",
    "created_at": "2023-10-05",
    "last_active": "2023-10-20"
  }
]
